krrez/.pylintrc
krrez/krrez_cli.py
krrez/requirements.txt
krrez/runtime-requirements.txt
krrez/api/__init__.py
krrez/api/internal.py
krrez/asset/__init__.py
krrez/asset/_pip.deploy_info.py
krrez/asset/data.py
krrez/asset/deploy_info.py
krrez/asset/project_info.py
krrez/asset/_static/krrez.png
krrez/asset/_static/README/en.pdf
krrez/bits/net/ssh/__init__.py
krrez/bits/seed/common.py
krrez/bits/seed/os/debian.py
krrez/bits/seed/steps/bootloader/__init__.py
krrez/bits/seed/steps/debootstrap/__init__.py
krrez/bits/seed/steps/disks/__init__.py
krrez/bits/seed/steps/drivers/__init__.py
krrez/bits/seed/steps/final_reboot/__init__.py
krrez/bits/seed/steps/first_boot/__init__.py
krrez/bits/seed/steps/hostname/__init__.py
krrez/bits/seed/steps/indirect/__init__.py
krrez/bits/seed/steps/keyboard/__init__.py
krrez/bits/seed/steps/krrez_bits/__init__.py
krrez/bits/seed/steps/locale/__init__.py
krrez/bits/seed/steps/machine_architecture/__init__.py
krrez/bits/seed/steps/machine_architecture/-data/bananapro/sun7i-a20-bananapro.dtb
krrez/bits/seed/steps/machine_architecture/-data/bananapro/u-boot-sunxi-with-spl.bin
krrez/bits/seed/steps/machine_architecture/-data/pinephone/u-boot-sunxi-with-spl.bin
krrez/bits/seed/steps/networking/__init__.py
krrez/bits/seed/steps/seed_user/__init__.py
krrez/bits/seed/steps/system_mounts/__init__.py
krrez/bits/seed/steps/timezone/__init__.py
krrez/bits/sys/config.py
krrez/bits/sys/fs.py
krrez/bits/sys/helpers.py
krrez/bits/sys/next_boot.py
krrez/bits/sys/packages.py
krrez/bits/sys/services.py
krrez/bits/sys/system_users.py
krrez/bits/sys/can_seed/__init__.py
krrez/bits/sys/can_seed/reseed/__init__.py
krrez/bits/sys/can_seed/reseed/-data/-reseed_update_handlers/50_krrez_via_pip.py
krrez/bits/sys/increase_system_users_range/__init__.py
krrez/bits/sys/machine_avatar/__init__.py
krrez/bits/sys/machine_avatar/-data/krrez_machine_avatar.py
krrez/bits/zz_test/zz_run/__init__.py
krrez/bits/zz_test/zz_run/_libvirt.py
krrez/bits/zz_test/zz_run/_machine.py
krrez-10.0.1292.dist-info/METADATA
krrez-10.0.1292.dist-info/WHEEL
krrez-10.0.1292.dist-info/entry_points.txt
krrez-10.0.1292.dist-info/top_level.txt
krrez-10.0.1292.dist-info/RECORD
