Metadata-Version: 2.4
Name: krrez
Version: 10.0.1292
Summary: Infrastructure-as-code framework for personal computers
Home-page: https://pseudopolis.eu/pino/krrez
Author: Josef Hahn
Author-email: krrez@pseudopolis.eu
License: AGPL 3
Keywords: iac infrastructure as code devops provisioning
Requires-Dist: libvirt-python>=9.0.0
Requires-Dist: pygraphviz~=1.10
Requires-Dist: fabric~=3.0
Requires-Dist: paramiko~=3.1
Requires-Dist: hallyd~=0.90
Requires-Dist: klovve~=1.1
Requires-Dist: watchdog~=4.0
Dynamic: author
Dynamic: author-email
Dynamic: description
Dynamic: description-content-type
Dynamic: home-page
Dynamic: keywords
Dynamic: license
Dynamic: requires-dist
Dynamic: summary
